evolven/__init__.py
evolven/api/__init__.py
evolven/api/api.py
evolven/api/res/__init__.py
evolven/api/res/api_base.py
evolven/api/res/api_result.py
evolven/api/res/appdef.py
evolven/api/res/blended.py
evolven/api/res/change.py
evolven/api/res/configuration.py
evolven/api/res/environment.py
evolven/api/res/eql.py
evolven/api/res/host.py
evolven/api/res/login.py
evolven/api/res/policy.py
evolven/api/res/search.py
evolven-1.1.0.dist-info/METADATA
evolven-1.1.0.dist-info/WHEEL
evolven-1.1.0.dist-info/top_level.txt
evolven-1.1.0.dist-info/RECORD
