Metadata-Version: 2.1
Name: evolven
Version: 1.1.0
Summary: Evolven API Python Client
Home-page: https://github.com/evolven-software/evolven-api-python
Author: Evolven Data Science Team
Author-email: bostjan@evolven.com
License: MIT
Keywords: evolven api development
Platform: UNKNOWN
Classifier: Development Status :: 4 - Beta
Classifier: Intended Audience :: Developers
Classifier: Topic :: Software Development :: Libraries
Classifier: Topic :: Scientific/Engineering :: Information Analysis
Classifier: License :: OSI Approved :: MIT License
Classifier: Programming Language :: Python :: 2
Classifier: Programming Language :: Python :: 2.6
Classifier: Programming Language :: Python :: 2.7
